perturb_tools/__init__.py
perturb_tools/_arithmetic/__init__.py
perturb_tools/_arithmetic/_funcs/_SequenceManipulation.py
perturb_tools/_arithmetic/_funcs/__init__.py
perturb_tools/_arithmetic/_funcs/_log_fold_change.py
perturb_tools/_arithmetic/_funcs/_LogFoldChange/_LogFoldChange_Module.py
perturb_tools/_arithmetic/_funcs/_LogFoldChange/__init__.py
perturb_tools/_arithmetic/_funcs/_LogFoldChange/_calculate_log_fold_change.py
perturb_tools/_experimental_design/__init__.py
perturb_tools/_experimental_design/_coding/__init__.py
perturb_tools/_experimental_design/_coding/_funcs/__init__.py
perturb_tools/_experimental_design/_coding/_funcs/_plot_CDS.py
perturb_tools/_experimental_design/_funcs/__init__.py
perturb_tools/_experimental_design/_general/_GTF_Module.py
perturb_tools/_experimental_design/_general/_TargetModule.py
perturb_tools/_experimental_design/_general/__init__.py
perturb_tools/_experimental_design/_general/_add_region_labels.py
perturb_tools/_experimental_design/_general/_add_sgRNA_context.py
perturb_tools/_experimental_design/_general/_annotate_guide_biochemistry.py
perturb_tools/_experimental_design/_general/_annotate_protospacer.py
perturb_tools/_experimental_design/_general/_get_chromosome_sequence.py
perturb_tools/_experimental_design/_general/_get_screen_target_features.py
perturb_tools/_experimental_design/_general/_identify_overlapping_fragments.py
perturb_tools/_experimental_design/_general/_make_guide_library_df.py
perturb_tools/_experimental_design/_general/_query_region_for_PAM.py
perturb_tools/_experimental_design/_general/_scan_for_BsmbI.py
perturb_tools/_experimental_design/_general/_widen_regions.py
perturb_tools/_external_tools/__init__.py
perturb_tools/_framework/_ScreenModule.py
perturb_tools/_framework/__init__.py
perturb_tools/_framework/_supporting_functions/__init__.py
perturb_tools/_framework/_supporting_functions/_print_screen_object.py
perturb_tools/_framework/_supporting_functions/_read_write_poolQ.py
perturb_tools-0.3.5.dist-info/LICENSE
perturb_tools-0.3.5.dist-info/METADATA
perturb_tools-0.3.5.dist-info/WHEEL
perturb_tools-0.3.5.dist-info/top_level.txt
perturb_tools-0.3.5.dist-info/RECORD
