Metadata-Version: 2.1
Name: perturb-tools
Version: 0.3.5
Summary: perturb-tools - Analysis Framework for Pooled CRISPR Genome Editing Screens.
Home-page: https://github.com/pinellolab/perturb-tools
Author: ['Michael E. Vinyard - Harvard University - Massachussetts General Hospital - Broad Institute of MIT and Harvard', 'Jayoung K. Ryu - Harvard University - Massachussetts General Hospital - Broad Institute of MIT and Harvard']
Author-email: Michael Vinyard <mvinyard@broadinstitute.org>, Jayoung Ryu <jayoung_ryu@g.harvard.edu>
License: MIT License
Project-URL: Homepage, https://github.com/pinellolab/perturb-tools
Project-URL: Issues, https://github.com/pinellolab/perturb-tools/issues
Classifier: Programming Language :: Python :: 3
Classifier: License :: OSI Approved :: MIT License
Classifier: Operating System :: OS Independent
Requires-Python: >3.7.0
License-File: LICENSE
Requires-Dist: matplotlib >=3.4
Requires-Dist: anndata >=0.7.1
Requires-Dist: numpy >=1.19.2
Requires-Dist: pandas >=1.1.2
Requires-Dist: biopython >=1.79
Requires-Dist: plotly
Requires-Dist: regex
Requires-Dist: xlsxwriter
